{
  "version": 0.6,
  "generator": "Overpass API 0.7.62.8 e802775f",
  "osm3s": {
    "timestamp_osm_base": "2025-08-29T10:07:36Z",
    "copyright": "The data included in this document is from www.openstreetmap.org. The data is made available under ODbL."
  },
  "elements": [
    {
      "type": "way",
      "id": 25199160,
      "bounds": {
        "minlat": 39.9981266,
        "minlon": 116.5132943,
        "maxlat": 40.0027787,
        "maxlon": 116.5244405
      },
      "nodes": [
        274737434,
        274730585,
        9701741767,
        274730594,
        9701741768,
        274730606,
        9701741769,
        274730615,
        9701741770,
        274730624,
        274730635,
        3508077298,
        274730647,
        274730658,
        274730669,
        274730697,
        274730713,
        274730724,
        9703099461,
        9703099462,
        274730739,
        9703091695,
        9168398972,
        3508076128
      ],
      "geometry": [
        {
          "lat": 39.9981266,
          "lon": 116.5132943
        },
        {
          "lat": 39.9985448,
          "lon": 116.5137575
        },
        {
          "lat": 39.9987773,
          "lon": 116.5140312
        },
        {
          "lat": 39.998976,
          "lon": 116.5142825
        },
        {
          "lat": 39.9992147,
          "lon": 116.5145921
        },
        {
          "lat": 39.9994008,
          "lon": 116.5148451
        },
        {
          "lat": 39.9996647,
          "lon": 116.5152226
        },
        {
          "lat": 39.999881,
          "lon": 116.5155517
        },
        {
          "lat": 40.0000649,
          "lon": 116.515864
        },
        {
          "lat": 40.0002266,
          "lon": 116.5161314
        },
        {
          "lat": 40.0003862,
          "lon": 116.5164094
        },
        {
          "lat": 40.0005297,
          "lon": 116.5166802
        },
        {
          "lat": 40.0009787,
          "lon": 116.5175147
        },
        {
          "lat": 40.0013626,
          "lon": 116.5184089
        },
        {
          "lat": 40.0017401,
          "lon": 116.519449
        },
        {
          "lat": 40.0019897,
          "lon": 116.5202252
        },
        {
          "lat": 40.0022333,
          "lon": 116.5211048
        },
        {
          "lat": 40.0023128,
          "lon": 116.5214544
        },
        {
          "lat": 40.0024288,
          "lon": 116.5219792
        },
        {
          "lat": 40.0025099,
          "lon": 116.5224084
        },
        {
          "lat": 40.0025729,
          "lon": 116.5227692
        },
        {
          "lat": 40.0026576,
          "lon": 116.5233503
        },
        {
          "lat": 40.0027333,
          "lon": 116.5239498
        },
        {
          "lat": 40.0027787,
          "lon": 116.5244405
        }
      ],
      "tags": {
        "electrified": "contact_line",
        "frequency": "50",
        "gauge": "1435",
        "maxspeed": "200",
        "railway": "rail",
        "railway:track_ref": "大环线",
        "usage": "test",
        "voltage": "25000"
      }
    }
  ]
}